Metadata-Version: 2.1
Name: zack_liu_package3
Version: 1.1.1
Summary: zack_liu_package
Home-page: https://github.com/liuzhimin2019/soho-ui.git
Author: zack_liu
Author-email: liu.zhimin.2019@gmail.com
License: BSD License
Platform: all
Classifier: Intended Audience :: Developers
Classifier: Operating System :: OS Independent
Requires-Python: >=3.7
License-File: LICENSE
